crc64iso/__init__.py
crc64iso/crc64iso.py
crc64iso-0.0.2.dist-info/METADATA
crc64iso-0.0.2.dist-info/RECORD
crc64iso-0.0.2.dist-info/WHEEL
crc64iso-0.0.2.dist-info/top_level.txt
