Metadata-Version: 2.1
Name: crc64iso
Version: 0.0.2
Summary: CRC-64 checksum generator
Home-page: UNKNOWN
Author: Bert Lievrouw
Author-email: bert.lievrouw@gmail.com
License: UNKNOWN
Keywords: checksum digest crc crc-64 cyclic redundancy check data integrity
Platform: UNKNOWN
Classifier: Programming Language :: Python :: 3
Classifier: License :: OSI Approved :: MIT License
Classifier: Operating System :: OS Independent
